opencv_plot/__init__.py
opencv_plot/main.py
opencv_plot-0.4.1.dist-info/METADATA
opencv_plot-0.4.1.dist-info/WHEEL
opencv_plot-0.4.1.dist-info/entry_points.txt
opencv_plot-0.4.1.dist-info/top_level.txt
opencv_plot-0.4.1.dist-info/RECORD
