Metadata-Version: 2.4
Name: opencv-plot
Version: 0.4.1
Summary: Dora Node for plotting text and bbox on image with OpenCV
Author-email: Haixuan Xavier Tao <tao.xavier@outlook.com>, Enzo Le Van <dev@enzo-le-van.fr>
Requires-Python: >=3.8
Requires-Dist: dora-rs>=0.3.9
Requires-Dist: numpy<2.0.0
Requires-Dist: opencv-python>=4.1.1
Requires-Dist: pillow-avif-plugin>=1.5.1
Requires-Dist: pillow>=10.4.0
